MANIFEST.in
README.md
dev.txt
setup.py
dole/__init__.py
dole/azure.py
dole/health.py
dole/redis.py
dole/version_info.py
dole.egg-info/PKG-INFO
dole.egg-info/SOURCES.txt
dole.egg-info/dependency_links.txt
dole.egg-info/requires.txt
dole.egg-info/top_level.txt